{
  "Date": "2021-07-07 13-01-36",
  "Type": "NORMAL",
  "Count": 152,
  "Items": [
    {
      "PageName": "root",
      "OfferId": -1,
      "PageId": -1
    },
    {
      "PageName": "front_page",
      "OfferId": -1,
      "PageId": 967927
    },
    {
      "PageName": "furni",
      "OfferId": -1,
      "PageId": -1
    },
    {
      "PageName": "credit_exchange",
      "OfferId": 18513,
      "PageId": 967964
    },
    {
      "PageName": "2020_hotnow",
      "OfferId": -1,
      "PageId": -1
    },
    {
      "PageName": "jul21low",
      "OfferId": 18903,
      "PageId": 967966
    },
    {
      "PageName": "jul21low3",
      "OfferId": -1,
      "PageId": 967967
    },
    {
      "PageName": "jul21high",
      "OfferId": 18901,
      "PageId": 967968
    },
    {
      "PageName": "jul21high3",
      "OfferId": -1,
      "PageId": 967969
    },
    {
      "PageName": "jul17old",
      "OfferId": 9897,
      "PageId": 967970
    },
    {
      "PageName": "bc_palooza",
      "OfferId": 14060,
      "PageId": 967971
    },
    {
      "PageName": "jun17new",
      "OfferId": 14912,
      "PageId": 967972
    },
    {
      "PageName": "bc_tiki",
      "OfferId": 13916,
      "PageId": 967973
    },
    {
      "PageName": "gameset_football",
      "OfferId": 13924,
      "PageId": 967974
    },
    {
      "PageName": "hot_furni",
      "OfferId": 13552,
      "PageId": 967975
    },
    {
      "PageName": "2020_roombundles",
      "OfferId": -1,
      "PageId": -1
    },
    {
      "PageName": "jan20sweet",
      "OfferId": 17344,
      "PageId": 967977
    },
    {
      "PageName": "jan20sweet2",
      "OfferId": 17346,
      "PageId": 967978
    },
    {
      "PageName": "jan20sweet3",
      "OfferId": 17342,
      "PageId": 967979
    },
    {
      "PageName": "jul21ba",
      "OfferId": 19112,
      "PageId": 967980
    },
    {
      "PageName": "jul21ba2",
      "OfferId": 19110,
      "PageId": 967981
    },
    {
      "PageName": "may21baby1",
      "OfferId": 18861,
      "PageId": 967982
    },
    {
      "PageName": "may21baby3",
      "OfferId": 18855,
      "PageId": 967983
    },
    {
      "PageName": "may21baby4",
      "OfferId": 18857,
      "PageId": 967984
    },
    {
      "PageName": "may21baby5",
      "OfferId": 18853,
      "PageId": 967985
    },
    {
      "PageName": "may21baby2",
      "OfferId": 18859,
      "PageId": 967986
    },
    {
      "PageName": "room_ad",
      "OfferId": 7290,
      "PageId": 967988
    },
    {
      "PageName": "2020_bytype",
      "OfferId": -1,
      "PageId": -1
    },
    {
      "PageName": "bots",
      "OfferId": 7299,
      "PageId": 967990
    },
    {
      "PageName": "wired_triggers",
      "OfferId": 4981,
      "PageId": 967991
    },
    {
      "PageName": "wired_effects",
      "OfferId": 4963,
      "PageId": 967992
    },
    {
      "PageName": "wired_conditions",
      "OfferId": 6330,
      "PageId": 967993
    },
    {
      "PageName": "wired_addons",
      "OfferId": 13459,
      "PageId": 967994
    },
    {
      "PageName": "wired_leaderboard",
      "OfferId": 8050,
      "PageId": 967995
    },
    {
      "PageName": "sound_fx",
      "OfferId": 7364,
      "PageId": 967996
    },
    {
      "PageName": "trax_jukebox",
      "OfferId": 13448,
      "PageId": 967997
    },
    {
      "PageName": "trax_songs",
      "OfferId": 14345,
      "PageId": 967998
    },
    {
      "PageName": "set_extras",
      "OfferId": 13499,
      "PageId": 967999
    },
    {
      "PageName": "badge_display",
      "OfferId": 7944,
      "PageId": 968000
    },
    {
      "PageName": "dynamic_product_category_bed",
      "OfferId": -1,
      "PageId": 968001
    },
    {
      "PageName": "set_rugs",
      "OfferId": 13464,
      "PageId": 968002
    },
    {
      "PageName": "dynamic_product_category_chair",
      "OfferId": -1,
      "PageId": 968003
    },
    {
      "PageName": "set_dimmer",
      "OfferId": 13347,
      "PageId": 968004
    },
    {
      "PageName": "dynamic_product_category_vending_machine",
      "OfferId": -1,
      "PageId": 968005
    },
    {
      "PageName": "dynamic_product_category_divider",
      "OfferId": -1,
      "PageId": 968006
    },
    {
      "PageName": "dynamic_product_category_floor",
      "OfferId": -1,
      "PageId": 968007
    },
    {
      "PageName": "space_floor",
      "OfferId": 5626,
      "PageId": 968008
    },
    {
      "PageName": "space_landscape",
      "OfferId": 7789,
      "PageId": 968010
    },
    {
      "PageName": "dynamic_product_category_lighting",
      "OfferId": -1,
      "PageId": 968011
    },
    {
      "PageName": "set_rollers",
      "OfferId": 13425,
      "PageId": 968012
    },
    {
      "PageName": "dynamic_product_category_table",
      "OfferId": -1,
      "PageId": 968013
    },
    {
      "PageName": "set_teleports2",
      "OfferId": 13420,
      "PageId": 968014
    },
    {
      "PageName": "palooza_tents",
      "OfferId": 13367,
      "PageId": 968015
    },
    {
      "PageName": "set_trophies",
      "OfferId": 433,
      "PageId": 968017
    },
    {
      "PageName": "set_posters",
      "OfferId": 13621,
      "PageId": 968018
    },
    {
      "PageName": "space_wallpaper",
      "OfferId": 5466,
      "PageId": 968019
    },
    {
      "PageName": "set_windows",
      "OfferId": 13391,
      "PageId": 968020
    },
    {
      "PageName": "2020_bydesign",
      "OfferId": -1,
      "PageId": -1
    },
    {
      "PageName": "set_anna",
      "OfferId": 13596,
      "PageId": 968028
    },
    {
      "PageName": "set_pixelnew",
      "OfferId": 13577,
      "PageId": 968034
    },
    {
      "PageName": "set_bath",
      "OfferId": 13517,
      "PageId": 968036
    },
    {
      "PageName": "set_picnic",
      "OfferId": 13547,
      "PageId": 968046
    },
    {
      "PageName": "set_cubie",
      "OfferId": 13521,
      "PageId": 968047
    },
    {
      "PageName": "bc_gardening",
      "OfferId": 8395,
      "PageId": 968052
    },
    {
      "PageName": "bc_university",
      "OfferId": 13645,
      "PageId": 968058
    },
    {
      "PageName": "healthspa",
      "OfferId": 13621,
      "PageId": 968060
    },
    {
      "PageName": "set_iced",
      "OfferId": 13610,
      "PageId": 968061
    },
    {
      "PageName": "ktchn15",
      "OfferId": 13699,
      "PageId": 968066
    },
    {
      "PageName": "set_lodge",
      "OfferId": 3214,
      "PageId": 968067
    },
    {
      "PageName": "set_mode",
      "OfferId": 13705,
      "PageId": 968071
    },
    {
      "PageName": "set_neon",
      "OfferId": 13725,
      "PageId": 968074
    },
    {
      "PageName": "set_pool",
      "OfferId": 13997,
      "PageId": 968077
    },
    {
      "PageName": "set_pura",
      "OfferId": 13729,
      "PageId": 968082
    },
    {
      "PageName": "hb20rain",
      "OfferId": 17707,
      "PageId": 968083
    },
    {
      "PageName": "set_usva",
      "OfferId": 8701,
      "PageId": 968100
    },
    {
      "PageName": "2020_byenvironment",
      "OfferId": -1,
      "PageId": -1
    },
    {
      "PageName": "guild_frontpage",
      "OfferId": -1,
      "PageId": 968108
    },
    {
      "PageName": "guild_custom_furni",
      "OfferId": 13380,
      "PageId": 968109
    },
    {
      "PageName": "guild_forum",
      "OfferId": 9300,
      "PageId": 968110
    },
    {
      "PageName": "dynamic_product_environment_bathroom",
      "OfferId": -1,
      "PageId": 968111
    },
    {
      "PageName": "dynamic_product_environment_countryside",
      "OfferId": -1,
      "PageId": 968112
    },
    {
      "PageName": "dynamic_product_environment_kitchen",
      "OfferId": -1,
      "PageId": 968113
    },
    {
      "PageName": "monkey_furni",
      "OfferId": 13424,
      "PageId": 968114
    },
    {
      "PageName": "dynamic_product_environment_nature",
      "OfferId": -1,
      "PageId": 968115
    },
    {
      "PageName": "gameset_battle_banzai",
      "OfferId": 13429,
      "PageId": 968116
    },
    {
      "PageName": "gameset_freeze",
      "OfferId": 13463,
      "PageId": 968117
    },
    {
      "PageName": "gameset_snowboard",
      "OfferId": 13586,
      "PageId": 968118
    },
    {
      "PageName": "gameset_ice_hockey",
      "OfferId": 13518,
      "PageId": 968119
    },
    {
      "PageName": "gameset_ice_tagging",
      "OfferId": 13764,
      "PageId": 968120
    },
    {
      "PageName": "gameset_roller_skates",
      "OfferId": 5186,
      "PageId": 968121
    },
    {
      "PageName": "2020_hcexclusives",
      "OfferId": -1,
      "PageId": -1
    },
    {
      "PageName": "club_shop",
      "OfferId": 13376,
      "PageId": 968123
    },
    {
      "PageName": "set_blackhole",
      "OfferId": 13449,
      "PageId": 968124
    },
    {
      "PageName": "marketplace_info",
      "OfferId": -1,
      "PageId": 968125
    },
    {
      "PageName": "martketplace_my_sales",
      "OfferId": -1,
      "PageId": 968126
    },
    {
      "PageName": "marketplace_offers",
      "OfferId": -1,
      "PageId": 968127
    },
    {
      "PageName": "clothing",
      "OfferId": -1,
      "PageId": -1
    },
    {
      "PageName": "clothing_new",
      "OfferId": 18837,
      "PageId": 968129
    },
    {
      "PageName": "clothing_outfits",
      "OfferId": 13382,
      "PageId": 968130
    },
    {
      "PageName": "clothing_hairstyles",
      "OfferId": 13446,
      "PageId": 968131
    },
    {
      "PageName": "clothing_hats",
      "OfferId": 13439,
      "PageId": 968132
    },
    {
      "PageName": "clothing_accessories",
      "OfferId": 13451,
      "PageId": 968133
    },
    {
      "PageName": "clothing_dresses",
      "OfferId": 14336,
      "PageId": 968134
    },
    {
      "PageName": "clothing_shirts",
      "OfferId": 14341,
      "PageId": 968135
    },
    {
      "PageName": "clothing_jackets",
      "OfferId": 13435,
      "PageId": 968136
    },
    {
      "PageName": "clothing_trousers",
      "OfferId": 13417,
      "PageId": 968137
    },
    {
      "PageName": "clothing_skirts",
      "OfferId": 13416,
      "PageId": 968138
    },
    {
      "PageName": "clothing_shoes",
      "OfferId": 14333,
      "PageId": 968139
    },
    {
      "PageName": "ny2015_permeffects",
      "OfferId": 14348,
      "PageId": 968140
    },
    {
      "PageName": "temp_effects",
      "OfferId": 18051,
      "PageId": 968141
    },
    {
      "PageName": "pets_new",
      "OfferId": -1,
      "PageId": -1
    },
    {
      "PageName": "pets_info",
      "OfferId": -1,
      "PageId": 968143
    },
    {
      "PageName": "golden_cow",
      "OfferId": 14976,
      "PageId": 968144
    },
    {
      "PageName": "pet_cow",
      "OfferId": 14909,
      "PageId": 968145
    },
    {
      "PageName": "pet_gnome",
      "OfferId": 8788,
      "PageId": 968146
    },
    {
      "PageName": "pet_chick",
      "OfferId": 5430,
      "PageId": 968147
    },
    {
      "PageName": "candyland15_obbah",
      "OfferId": 11783,
      "PageId": 968148
    },
    {
      "PageName": "pet_horse",
      "OfferId": 6122,
      "PageId": 968149
    },
    {
      "PageName": "pet_monkey",
      "OfferId": 5978,
      "PageId": 968150
    },
    {
      "PageName": "pet_raptor",
      "OfferId": 12042,
      "PageId": 968151
    },
    {
      "PageName": "pet_pterosaur",
      "OfferId": 12043,
      "PageId": 968152
    },
    {
      "PageName": "pet_polar_bear",
      "OfferId": 4213,
      "PageId": 968153
    },
    {
      "PageName": "pet_dragon",
      "OfferId": 5848,
      "PageId": 968154
    },
    {
      "PageName": "pet_terrier",
      "OfferId": 4212,
      "PageId": 968155
    },
    {
      "PageName": "pet_lion",
      "OfferId": 4760,
      "PageId": 968156
    },
    {
      "PageName": "pet_turtle",
      "OfferId": 5934,
      "PageId": 968157
    },
    {
      "PageName": "pet_crocodile",
      "OfferId": 1316,
      "PageId": 968158
    },
    {
      "PageName": "pet_rhino",
      "OfferId": 4761,
      "PageId": 968159
    },
    {
      "PageName": "pet_spider",
      "OfferId": 5251,
      "PageId": 968160
    },
    {
      "PageName": "pet_dog",
      "OfferId": 456,
      "PageId": 968161
    },
    {
      "PageName": "pet_cat",
      "OfferId": 457,
      "PageId": 968162
    },
    {
      "PageName": "pet_boar",
      "OfferId": 4214,
      "PageId": 968163
    },
    {
      "PageName": "pet_frog",
      "OfferId": 5266,
      "PageId": 968164
    },
    {
      "PageName": "babypets_info",
      "OfferId": -1,
      "PageId": 968166
    },
    {
      "PageName": "pet_puppy",
      "OfferId": 10032,
      "PageId": 968167
    },
    {
      "PageName": "pet_kitten",
      "OfferId": 10031,
      "PageId": 968168
    },
    {
      "PageName": "pet_piglet",
      "OfferId": 10033,
      "PageId": 968169
    },
    {
      "PageName": "pets_pet_equipment",
      "OfferId": -1,
      "PageId": -1
    },
    {
      "PageName": "baby_pet_accessories",
      "OfferId": 7794,
      "PageId": 968172
    },
    {
      "PageName": "horse_saddle",
      "OfferId": 6232,
      "PageId": 968173
    },
    {
      "PageName": "horse_dyes",
      "OfferId": 13469,
      "PageId": 968174
    },
    {
      "PageName": "horse_styles",
      "OfferId": 13381,
      "PageId": 968175
    },
    {
      "PageName": "horse_jump_pilot",
      "OfferId": 13369,
      "PageId": 968176
    },
    {
      "PageName": "monster_plants_info",
      "OfferId": -1,
      "PageId": 968177
    },
    {
      "PageName": "monster_plant_seeds",
      "OfferId": 8422,
      "PageId": 968178
    },
    {
      "PageName": "monster_plant_potions",
      "OfferId": 8433,
      "PageId": 968179
    },
    {
      "PageName": "habbo_club_desktop",
      "OfferId": -1,
      "PageId": -1
    },
    {
      "PageName": "hc_membership",
      "OfferId": -1,
      "PageId": 968181
    },
    {
      "PageName": "builders_club_frontpage",
      "OfferId": 8807,
      "PageId": 968182
    },
    {
      "PageName": "loyalty_bc",
      "OfferId": 9433,
      "PageId": 968183
    },
    {
      "PageName": "builders_upgrades",
      "OfferId": 8758,
      "PageId": 968184
    },
    {
      "PageName": "bchc_boxes",
      "OfferId": 15640,
      "PageId": 968185
    }
  ]
}